{"books": [{"count": 1, "publish home": "moscow", "year": 1994, "id": 1, "author": "pushkin", "name": "hello"}, {"count": 63, "publish home": "moscow", "year": 1898, "id": 3, "author": "tolstoy", "name": "another name"}, {"count": 24, "publish home": "moscow", "year": 1848, "id": 2, "author": "ogon", "name": "name"}, {"count": 23, "publish home": "Moscow", "year": 1987, "id": 0, "author": "Sergey F", "name": "my book"}, {"count": 63, "publish home": "Boston", "year": 1943, "id": 0, "author": "SergeF", "name": "Under F"}, {"count": 12, "publish home": "gaza", "year": 2017, "id": 0, "author": "volna", "name": "novay"}, {"count": 42, "publish home": "piter", "year": 1982, "id": 0, "author": "Karenina", "name": "Annd"}, {"count": 23, "publish home": "Sib", "year": "1994", "id": 0, "author": "dedmoroz", "name": "DedMoroz"}, {"count": 72, "publish home": "hersory", "year": 1823, "id": 0, "author": "Snik", "name": "Bum"}, {"count": 7, "publish home": "zxv", "year": "1994", "id": 0, "author": "poiu", "name": "erw"}, {"count": 778, "publish home": "vvvvv", "year": "1994", "id": 0, "author": "kendrick", "name": "pqwer"}, {"count": 1, "publish home": "Groz", "year": 1872, "id": 1515695481518, "author": "Semen", "name": "Shast"}, {"count": 1, "publish home": "BigDom", "year": 7342, "id": 1515696257676, "author": "Super", "name": "listOfVal"}, {"id": 1515709192659, "publish home": "red", "year": 1234, "author": "int", "name": "qwerty", "count": 1}]}